day_trading_models/__init__.py
day_trading_models/database.py
day_trading_models/models/__init__.py
day_trading_models/models/date.py
day_trading_models/models/dt.py
day_trading_models/models/fund.py
day_trading_models/models/lhb.py
day_trading_models/models/lhb_hyyyb.py
day_trading_models/models/lhb_player.py
day_trading_models/models/quotation.py
day_trading_models/models/strong.py
day_trading_models/models/subnew.py
day_trading_models/models/zb.py
day_trading_models/models/zt.py
day_trading_models-0.1.0.dist-info/LICENSE
day_trading_models-0.1.0.dist-info/METADATA
day_trading_models-0.1.0.dist-info/WHEEL
day_trading_models-0.1.0.dist-info/top_level.txt
day_trading_models-0.1.0.dist-info/RECORD
