Metadata-Version: 2.1
Name: day_trading_models
Version: 0.1.0
Summary: SQL models for day trading
Author-email: Andimeo <andimeo@foxmail.com>
Project-URL: Homepage, https://github.com/Andimeo/day-trading-models
Classifier: Programming Language :: Python :: 3
Classifier: License :: OSI Approved :: MIT License
Classifier: Operating System :: OS Independent
Requires-Python: >=3.6
License-File: LICENSE
Requires-Dist: sqlalchemy>=2.0.0
Provides-Extra: dev
Requires-Dist: pytest; extra == "dev"
